zoome/__init__.py
zoome/api.py
zoome/utils.py
zoome-0.0.5.dist-info/LICENSE
zoome-0.0.5.dist-info/METADATA
zoome-0.0.5.dist-info/WHEEL
zoome-0.0.5.dist-info/top_level.txt
zoome-0.0.5.dist-info/RECORD
