Metadata-Version: 2.1
Name: zoome
Version: 0.0.5
Summary: Python library for easy using Zoom-API-v2
Home-page: https://github.com/2dlab/zoome
Author: Gusarov Vladislav
Author-email: tech@2dlab.ru
License: UNKNOWN
Platform: UNKNOWN
Classifier: Programming Language :: Python :: 3
Classifier: License :: OSI Approved :: MIT License
Classifier: Operating System :: OS Independent
Requires-Python: >=3.6
Requires-Dist: pyJWT (==2.0.0)
Requires-Dist: requests
